{"inkVersion":20,"root":[["^Pet: where are we?","\n","^Bot: dead maybe.","\n","^Pet: uhu, do not bring that up now.","\n","^Bot: ok ok, just calm down.","\n","^???: Well Well Well.","\n","^???: Congrats on finishing that level.","\n","^Pet: Hey you, what is going on.","\n","^???: Since you managed to finish that level you are qualified to move to the next arena.","\n","^Pet: HE IS DEFINITELY IGNORING ME?","\n","^Bot: I guess so.","\n","^Pet: I wanna die.","\n",["done",{"#f":5,"#n":"g-0"}],null],"done",{"#f":1}],"listDefs":{}}